README.rst
setup.py
Marketplace.egg-info/PKG-INFO
Marketplace.egg-info/SOURCES.txt
Marketplace.egg-info/dependency_links.txt
Marketplace.egg-info/requires.txt
Marketplace.egg-info/top_level.txt
marketplace/__init__.py
marketplace/client.py
marketplace/connection.py