Metadata-Version: 1.0
Name: Marketplace
Version: 0.9.1
Summary: Firefox Marketplace Client Library
Home-page: https://github.com/mozilla/Marketplace.Python
Author: Piotr Zalewa
Author-email: zalun@mozilla.com
License: Mozilla Public License (MPL 2.0)
Platform: UNKNOWN
